lazy_flask/__init__.py
lazy_flask/app.py
lazy_flask/py.typed
lazy_flask-0.1.2.dist-info/LICENSE
lazy_flask-0.1.2.dist-info/METADATA
lazy_flask-0.1.2.dist-info/WHEEL
lazy_flask-0.1.2.dist-info/RECORD
