Metadata-Version: 2.3
Name: lazy-flask
Version: 0.1.2
Summary: A lightweight toolkit that simplifies the Flask development process, helping you quickly build Python web applications.
Author: wrl96
Author-email: ruilin.wang96@gmail.com
Requires-Python: >=3.9
Classifier: Programming Language :: Python :: 3
Classifier: Programming Language :: Python :: 3.9
Classifier: Programming Language :: Python :: 3.10
Classifier: Programming Language :: Python :: 3.11
Classifier: Programming Language :: Python :: 3.12
Classifier: Programming Language :: Python :: 3.13
Requires-Dist: flask (>=1.0.0)
Requires-Dist: lazy-core (==0.1.2)
Requires-Dist: pydantic (>=2.11.7,<3.0.0)
